README.txt
setup.cfg
setup.py
Products/__init__.py
Products.QuillsEnabled.egg-info/PKG-INFO
Products.QuillsEnabled.egg-info/SOURCES.txt
Products.QuillsEnabled.egg-info/dependency_links.txt
Products.QuillsEnabled.egg-info/entry_points.txt
Products.QuillsEnabled.egg-info/namespace_packages.txt
Products.QuillsEnabled.egg-info/not-zip-safe
Products.QuillsEnabled.egg-info/requires.txt
Products.QuillsEnabled.egg-info/top_level.txt
Products/QuillsEnabled/LICENSE.txt
Products/QuillsEnabled/README.txt
Products/QuillsEnabled/__init__.py
Products/QuillsEnabled/activation.py
Products/QuillsEnabled/config.py
Products/QuillsEnabled/configure.zcml
Products/QuillsEnabled/migrations.py
Products/QuillsEnabled/setuphandlers.py
Products/QuillsEnabled/syndication.zcml
Products/QuillsEnabled/traversal.py
Products/QuillsEnabled/traversal.zcml
Products/QuillsEnabled/version.txt
Products/QuillsEnabled/Extensions/Install.py
Products/QuillsEnabled/adapters/__init__.py
Products/QuillsEnabled/adapters/document.py
Products/QuillsEnabled/adapters/feedentry.py
Products/QuillsEnabled/adapters/folder.py
Products/QuillsEnabled/browser/__init__.py
Products/QuillsEnabled/browser/activation.py
Products/QuillsEnabled/browser/configure.zcml
Products/QuillsEnabled/browser/weblogconfig.py
Products/QuillsEnabled/browser/weblogview.py
Products/QuillsEnabled/profiles/default/actions.xml
Products/QuillsEnabled/profiles/default/import_steps.xml
Products/QuillsEnabled/profiles/default/metadata.xml
Products/QuillsEnabled/profiles/default/quillsenabled_product_various.txt
Products/QuillsEnabled/tests/__init__.py
Products/QuillsEnabled/tests/base.py
Products/QuillsEnabled/tests/browser.rst
Products/QuillsEnabled/tests/fixedBugs.rst
Products/QuillsEnabled/tests/openBugs.rst
Products/QuillsEnabled/tests/test_docfile.py
Products/QuillsEnabled/tests/test_doctests.py
Products/QuillsEnabled/tests/test_remoteblogging.py
Products/QuillsEnabled/tests/test_weblog.py
docs/HISTORY.txt
docs/INSTALL.txt
docs/LICENSE.GPL
docs/LICENSE.txt