Metadata-Version: 1.0
Name: Products.QuillsEnabled
Version: 1.8a1
Summary: A Blogging Suite for Plone.
Home-page: http://plone.org/products/quills
Author: Quills Team
Author-email: plone-quills@googlegroups.com
License: GPL
Download-URL: http://svn.plone.org/svn/collective/Products.Quills
Keywords: plone blogging
Platform: UNKNOWN
Classifier: Development Status :: 5 - Production/Stable
Classifier: Framework :: Plone
Classifier: License :: OSI Approved :: GNU General Public License (GPL)
Classifier: Programming Language :: Python
Classifier: Topic :: Software Development :: Libraries :: Python Modules
